LICENSE
MANIFEST.in
README.rst
setup.py
assets/favicon.xcf
docs/Makefile
docs/about.rst
docs/algorithm.rst
docs/apireference.rst
docs/conf.py
docs/index.rst
docs/installation.rst
docs/make.bat
docs/privacy.rst
docs/releasenotes.rst
docs/testing.rst
docs/usage.rst
docs/images/branko.png
docs/images/branko_inverted.png
docs/images/favicon.ico
docs/images/logo.png
docs/images/pydenticon.png
docs/images/pydenticon_inverted.png
pydenticon/__init__.py
pydenticon.egg-info/PKG-INFO
pydenticon.egg-info/SOURCES.txt
pydenticon.egg-info/dependency_links.txt
pydenticon.egg-info/requires.txt
pydenticon.egg-info/top_level.txt
tests/__init__.py
tests/test_pydenticon.py
tests/samples/test1.png
tests/samples/test2.png
tests/samples/test3.png