Metadata-Version: 1.1
Name: pydenticon
Version: 0.1.1
Summary: Library for generating identicons. Port of Sigil (https://github.com/cupcake/sigil) with enhancements.
Home-page: https://github.com/azaghal/pydenticon
Author: Branko Majic
Author-email: branko@majic.rs
License: BSD
Platform: UNKNOWN
Classifier: Environment :: Other Environment
Classifier: Environment :: Web Environment
Classifier: Intended Audience :: Developers
Classifier: License :: OSI Approved :: BSD License
Classifier: Operating System :: OS Independent
Classifier: Programming Language :: Python
Classifier: Programming Language :: Python :: 2.7
Classifier: Topic :: Internet :: WWW/HTTP :: Dynamic Content
Classifier: Topic :: Multimedia :: Graphics
Classifier: Topic :: Software Development :: Libraries
